<Properties StartupConfiguration="{23F80055-47C3-4A1C-BFF0-465B233F2556}|Default">
  <MonoDevelop.Ide.Workbench ActiveDocument="Application.vb">
    <Files>
      <File FileName="Application.vb" Line="1" Column="1" />
    </Files>
    <Pads>
      <Pad Id="ProjectPad">
        <State name="__root__">
          <Node name="exerc10" expanded="True">
            <Node name="exerc10" expanded="True">
              <Node name="Application.vb" selected="True" />
            </Node>
          </Node>
        </State>
      </Pad>
    </Pads>
  </MonoDevelop.Ide.Workbench>
  <MonoDevelop.Ide.DebuggingService.PinnedWatches />
  <MonoDevelop.Ide.Workspace ActiveConfiguration="Debug|anycpu" />
  <MonoDevelop.Ide.ItemProperties.exerc10 PreferredExecutionTarget="MonoDevelop.Default" />
  <MonoDevelop.Ide.DebuggingService.Breakpoints>
    <BreakpointStore />
  </MonoDevelop.Ide.DebuggingService.Breakpoints>
  <MultiItemStartupConfigurations />
</Properties>