<Properties StartupConfiguration="{442B84EF-8914-45D1-8C8B-C5B63AC37289}|Default">
  <MonoDevelop.Ide.Workbench ActiveDocument="Module1/Application.vb">
    <Files>
      <File FileName="Module1/Application.vb" Line="16" Column="3" />
    </Files>
    <Pads>
      <Pad Id="ProjectPad">
        <State name="__root__">
          <Node name="Module1" expanded="True">
            <Node name="Module1" expanded="True">
              <Node name="Application.vb" selected="True" />
            </Node>
          </Node>
        </State>
      </Pad>
    </Pads>
  </MonoDevelop.Ide.Workbench>
  <MonoDevelop.Ide.DebuggingService.PinnedWatches />
  <MonoDevelop.Ide.ItemProperties.Module1 PreferredExecutionTarget="MonoDevelop.Default" />
  <MonoDevelop.Ide.Workspace ActiveConfiguration="Debug|anycpu" />
  <MonoDevelop.Ide.DebuggingService.Breakpoints>
    <BreakpointStore />
  </MonoDevelop.Ide.DebuggingService.Breakpoints>
  <MultiItemStartupConfigurations />
</Properties>